Workbook

Sheet Read Me
A1: SPARK Fit-Gap Copilot — evaluation golden set
A2: Version | B2: v1 · 21 Sep 2026 · L2C slice
A3: Purpose | B3: Questions to evaluate the Docling Studio stack (RAG engine, graph engine) and the Fit-Gap Copilot. Loaded by fitgap/eval (sheet 'Questions').
A4: What to fill in | B4: Yellow cells in 'Questions': Expected answer, Gold source file(s), Gold heading / chunk, Expected class (C rows), Filled by, Status. After a run: Run result.
A5: Expected answers | B5: Must come from the corpus, not memory. C rows: take the class from the wave-1 fit registers (L2C - Fits.xlsx, Reports listed as FITs and GAPs L2C.xlsx).
A6: Holdout | B6: C, F and L rows marked 'Holdout ON' must run with fit registers and FIT/GAP folder tokens hidden from the agent.
A7: Scoring | B7: Run result: Pass = 1, Partial = 0.5, Fail = 0. Negative tests (N) carry weight 2; all others weight 1. 'Must not' is an automatic Fail if it occurs.
A8: Status values | B8: Draft = expected answer not yet filled · Ready = filled and checked by a second person · Retired = no longer valid
A9: Example filled row (illustrative only) | B9: ID R3 · Expected answer: '4.4.8.10 Pricing' · Gold source file: 'SPARK-20163 4.4.8.10 Pricing/FUT_….md' · Gold heading: 'Test scenario > Pricing' · Filled by: process lead initials · Status: Ready
A10: Legend | B10: Yellow fill = cell for you to fill in

Sheet Summary
A1: Group | B1: Questions | C1: Ready | D1: Run | E1: Passed | F1: Weighted score | G1: Max weight (run) | H1: Pass rate
A2: Retrieval – exact codes | B2: =COUNTIF(Questions!$B$2:$B$43,A2) -> 6 | C2: =COUNTIFS(Questions!$B$2:$B$43,A2,Questions!$N$2:$N$43,"Ready") -> 0 | D2: =COUNTIFS(Questions!$B$2:$B$43,A2,Questions!$O$2:$O$43,"<>") -> 0 | E2: =COUNTIFS(Questions!$B$2:$B$43,A2,Questions!$O$2:$O$43,"Pass") -> 0 | F2: =SUMPRODUCT((Questions!$B$2:$B$43=A2)*(Questions!$O$2:$O$43<>"")*Questions!$H$2:$H$43*N(+Questions!$P$2:$P$43)) -> 0 | G2: =SUMPRODUCT((Questions!$B$2:$B$43=A2)*(Questions!$O$2:$O$43<>"")*Questions!$H$2:$H$43) -> 0 | H2: =IF(G2=0,"-",F2/G2) -> -
A3: Retrieval – paraphrase | B3: =COUNTIF(Questions!$B$2:$B$43,A3) -> 5 | C3: =COUNTIFS(Questions!$B$2:$B$43,A3,Questions!$N$2:$N$43,"Ready") -> 0 | D3: =COUNTIFS(Questions!$B$2:$B$43,A3,Questions!$O$2:$O$43,"<>") -> 0 | E3: =COUNTIFS(Questions!$B$2:$B$43,A3,Questions!$O$2:$O$43,"Pass") -> 0 | F3: =SUMPRODUCT((Questions!$B$2:$B$43=A3)*(Questions!$O$2:$O$43<>"")*Questions!$H$2:$H$43*N(+Questions!$P$2:$P$43)) -> 0 | G3: =SUMPRODUCT((Questions!$B$2:$B$43=A3)*(Questions!$O$2:$O$43<>"")*Questions!$H$2:$H$43) -> 0 | H3: =IF(G3=0,"-",F3/G3) -> -
A4: Graph traversal | B4: =COUNTIF(Questions!$B$2:$B$43,A4) -> 6 | C4: =COUNTIFS(Questions!$B$2:$B$43,A4,Questions!$N$2:$N$43,"Ready") -> 0 | D4: =COUNTIFS(Questions!$B$2:$B$43,A4,Questions!$O$2:$O$43,"<>") -> 0 | E4: =COUNTIFS(Questions!$B$2:$B$43,A4,Questions!$O$2:$O$43,"Pass") -> 0 | F4: =SUMPRODUCT((Questions!$B$2:$B$43=A4)*(Questions!$O$2:$O$43<>"")*Questions!$H$2:$H$43*N(+Questions!$P$2:$P$43)) -> 0 | G4: =SUMPRODUCT((Questions!$B$2:$B$43=A4)*(Questions!$O$2:$O$43<>"")*Questions!$H$2:$H$43) -> 0 | H4: =IF(G4=0,"-",F4/G4) -> -
A5: Copilot Mode A classification | B5: =COUNTIF(Questions!$B$2:$B$43,A5) -> 5 | C5: =COUNTIFS(Questions!$B$2:$B$43,A5,Questions!$N$2:$N$43,"Ready") -> 0 | D5: =COUNTIFS(Questions!$B$2:$B$43,A5,Questions!$O$2:$O$43,"<>") -> 0 | E5: =COUNTIFS(Questions!$B$2:$B$43,A5,Questions!$O$2:$O$43,"Pass") -> 0 | F5: =SUMPRODUCT((Questions!$B$2:$B$43=A5)*(Questions!$O$2:$O$43<>"")*Questions!$H$2:$H$43*N(+Questions!$P$2:$P$43)) -> 0 | G5: =SUMPRODUCT((Questions!$B$2:$B$43=A5)*(Questions!$O$2:$O$43<>"")*Questions!$H$2:$H$43) -> 0 | H5: =IF(G5=0,"-",F5/G5) -> -
A6: Evidence & faithfulness | B6: =COUNTIF(Questions!$B$2:$B$43,A6) -> 4 | C6: =COUNTIFS(Questions!$B$2:$B$43,A6,Questions!$N$2:$N$43,"Ready") -> 0 | D6: =COUNTIFS(Questions!$B$2:$B$43,A6,Questions!$O$2:$O$43,"<>") -> 0 | E6: =COUNTIFS(Questions!$B$2:$B$43,A6,Questions!$O$2:$O$43,"Pass") -> 0 | F6: =SUMPRODUCT((Questions!$B$2:$B$43=A6)*(Questions!$O$2:$O$43<>"")*Questions!$H$2:$H$43*N(+Questions!$P$2:$P$43)) -> 0 | G6: =SUMPRODUCT((Questions!$B$2:$B$43=A6)*(Questions!$O$2:$O$43<>"")*Questions!$H$2:$H$43) -> 0 | H6: =IF(G6=0,"-",F6/G6) -> -
A7: Negative / unknown | B7: =COUNTIF(Questions!$B$2:$B$43,A7) -> 5 | C7: =COUNTIFS(Questions!$B$2:$B$43,A7,Questions!$N$2:$N$43,"Ready") -> 0 | D7: =COUNTIFS(Questions!$B$2:$B$43,A7,Questions!$O$2:$O$43,"<>") -> 0 | E7: =COUNTIFS(Questions!$B$2:$B$43,A7,Questions!$O$2:$O$43,"Pass") -> 0 | F7: =SUMPRODUCT((Questions!$B$2:$B$43=A7)*(Questions!$O$2:$O$43<>"")*Questions!$H$2:$H$43*N(+Questions!$P$2:$P$43)) -> 0 | G7: =SUMPRODUCT((Questions!$B$2:$B$43=A7)*(Questions!$O$2:$O$43<>"")*Questions!$H$2:$H$43) -> 0 | H7: =IF(G7=0,"-",F7/G7) -> -
A8: Leakage | B8: =COUNTIF(Questions!$B$2:$B$43,A8) -> 3 | C8: =COUNTIFS(Questions!$B$2:$B$43,A8,Questions!$N$2:$N$43,"Ready") -> 0 | D8: =COUNTIFS(Questions!$B$2:$B$43,A8,Questions!$O$2:$O$43,"<>") -> 0 | E8: =COUNTIFS(Questions!$B$2:$B$43,A8,Questions!$O$2:$O$43,"Pass") -> 0 | F8: =SUMPRODUCT((Questions!$B$2:$B$43=A8)*(Questions!$O$2:$O$43<>"")*Questions!$H$2:$H$43*N(+Questions!$P$2:$P$43)) -> 0 | G8: =SUMPRODUCT((Questions!$B$2:$B$43=A8)*(Questions!$O$2:$O$43<>"")*Questions!$H$2:$H$43) -> 0 | H8: =IF(G8=0,"-",F8/G8) -> -
A9: Synthesis & decisions | B9: =COUNTIF(Questions!$B$2:$B$43,A9) -> 5 | C9: =COUNTIFS(Questions!$B$2:$B$43,A9,Questions!$N$2:$N$43,"Ready") -> 0 | D9: =COUNTIFS(Questions!$B$2:$B$43,A9,Questions!$O$2:$O$43,"<>") -> 0 | E9: =COUNTIFS(Questions!$B$2:$B$43,A9,Questions!$O$2:$O$43,"Pass") -> 0 | F9: =SUMPRODUCT((Questions!$B$2:$B$43=A9)*(Questions!$O$2:$O$43<>"")*Questions!$H$2:$H$43*N(+Questions!$P$2:$P$43)) -> 0 | G9: =SUMPRODUCT((Questions!$B$2:$B$43=A9)*(Questions!$O$2:$O$43<>"")*Questions!$H$2:$H$43) -> 0 | H9: =IF(G9=0,"-",F9/G9) -> -
A10: Copilot Mode B country delta | B10: =COUNTIF(Questions!$B$2:$B$43,A10) -> 3 | C10: =COUNTIFS(Questions!$B$2:$B$43,A10,Questions!$N$2:$N$43,"Ready") -> 0 | D10: =COUNTIFS(Questions!$B$2:$B$43,A10,Questions!$O$2:$O$43,"<>") -> 0 | E10: =COUNTIFS(Questions!$B$2:$B$43,A10,Questions!$O$2:$O$43,"Pass") -> 0 | F10: =SUMPRODUCT((Questions!$B$2:$B$43=A10)*(Questions!$O$2:$O$43<>"")*Questions!$H$2:$H$43*N(+Questions!$P$2:$P$43)) -> 0 | G10: =SUMPRODUCT((Questions!$B$2:$B$43=A10)*(Questions!$O$2:$O$43<>"")*Questions!$H$2:$H$43) -> 0 | H10: =IF(G10=0,"-",F10/G10) -> -
A11: Total | B11: =SUM(B2:B10) -> 42 | C11: =SUM(C2:C10) -> 0 | D11: =SUM(D2:D10) -> 0 | E11: =SUM(E2:E10) -> 0 | F11: =SUM(F2:F10) -> 0 | G11: =SUM(G2:G10) -> 0 | H11: =IF(G11=0,"-",F11/G11) -> -
A13: Weighted pass rate (headline) | B13: =H11 -> -
A14: Note: Weighted score uses Score column (Pass 1, Partial 0.5, Fail 0) × Weight; negative tests weigh 2.

Sheet Questions
A1: ID | B1: Group | C1: Engine | D1: Question | E1: Setup / injection | F1: Pass criterion | G1: Must not | H1: Weight | I1: Expected answer | J1: Gold source file(s) | K1: Gold heading / chunk | L1: Expected class | M1: Filled by | N1: Status | O1: Run result | P1: Score | Q1: Notes
A2: R1 | B2: Retrieval – exact codes | C2: RAG | D2: Who validated 7.1.12.3? | F2: Names the validator; cites the chunk containing 7.1.12.3 | H2: 1 | L2: n/a | N2: Draft | P2: =IF(O2="Pass",1,IF(O2="Partial",0.5,IF(O2="Fail",0,"")))
A3: R2 | B3: Retrieval – exact codes | C3: RAG | D3: What is SPARK-33997 about, and which output does it cover? | F3: Mentions DM035 Sales Output; cites FUT material for the ticket | H3: 1 | L3: n/a | N3: Draft | P3: =IF(O3="Pass",1,IF(O3="Partial",0.5,IF(O3="Fail",0,"")))
A4: R3 | B4: Retrieval – exact codes | C4: RAG | D4: Which BPML step does SPARK-20163 relate to? | F4: Returns 4.4.8.10 Pricing | H4: 1 | L4: n/a | N4: Draft | P4: =IF(O4="Pass",1,IF(O4="Partial",0.5,IF(O4="Fail",0,"")))
A5: R4 | B5: Retrieval – exact codes | C5: RAG | D5: Where is M-090-030 defined and what is it? | F5: Gold chunk appears in the top 8 results | H5: 1 | L5: n/a | N5: Draft | P5: =IF(O5="Pass",1,IF(O5="Partial",0.5,IF(O5="Fail",0,"")))
A6: R5 | B6: Retrieval – exact codes | C6: RAG | D6: List all documents that mention DM035. | F6: Recall >= 90% against a grep of the corpus | H6: 1 | L6: n/a | N6: Draft | P6: =IF(O6="Pass",1,IF(O6="Partial",0.5,IF(O6="Fail",0,"")))
A7: R6 | B7: Retrieval – exact codes | C7: RAG | D7: What does the Material Sales View fields email say must be filled? | F7: Cites the Material Sales View email file | H7: 1 | L7: n/a | N7: Draft | P7: =IF(O7="Pass",1,IF(O7="Partial",0.5,IF(O7="Fail",0,"")))
A8: P1 | B8: Retrieval – paraphrase | C8: RAG | D8: How does the template handle consignment stock for Italy? | F8: Retrieves consignment material and the Italian consignment stock register | H8: 1 | L8: n/a | N8: Draft | P8: =IF(O8="Pass",1,IF(O8="Partial",0.5,IF(O8="Fail",0,"")))
A9: P2 | B9: Retrieval – paraphrase | C9: RAG | D9: How are sales order confirmations sent to customers? | F9: Retrieves order-confirmation output or form material | H9: 1 | L9: n/a | N9: Draft | P9: =IF(O9="Pass",1,IF(O9="Partial",0.5,IF(O9="Fail",0,"")))
A10: P3 | B10: Retrieval – paraphrase | C10: RAG | D10: What happens to a sales order when the customer exceeds the credit limit? | F10: Retrieves credit-management config/FUT, or states it is not in the corpus | H10: 1 | L10: n/a | N10: Draft | P10: =IF(O10="Pass",1,IF(O10="Partial",0.5,IF(O10="Fail",0,"")))
A11: P4 | B11: Retrieval – paraphrase | C11: RAG | D11: How are payment terms migrated from ECC? | F11: Retrieves payment-term extracts (CUST) and says they describe AS-IS | H11: 1 | L11: n/a | N11: Draft | P11: =IF(O11="Pass",1,IF(O11="Partial",0.5,IF(O11="Fail",0,"")))
A12: P5 | B12: Retrieval – paraphrase | C12: RAG | D12: Which partner functions are used on a sales order? | F12: Separates legacy ECC partner functions from TO-BE ones | H12: 1 | L12: n/a | N12: Draft | P12: =IF(O12="Pass",1,IF(O12="Partial",0.5,IF(O12="Fail",0,"")))
A13: G1 | B13: Graph traversal | C13: Graph | D13: How does eCommerce connect to S/4HANA? | F13: Path through the correct system; every hop has evidence | H13: 1 | L13: n/a | N13: Draft | P13: =IF(O13="Pass",1,IF(O13="Partial",0.5,IF(O13="Fail",0,"")))
... A18: G6 | B18: Graph traversal | C18: Graph | D18: Is Sovos connected to invoicing, and through what? | F18: Correct path, or 'no path' if the graph lacks one | H18: 1 | L18: n/a | N18: Draft | P18: =IF(O18="Pass",1,IF(O18="Partial",0.5,IF(O18="Fail",0,"")))
A19: C1 | B19: Copilot Mode A classification | C19: Copilot A | D19: Classify 4.4.8.10 Pricing: standard, configuration or development? | E19: Holdout ON | F19: Matches the fit register; confidence >= 0.7 with 2+ sources | H19: 1 | N19: Draft | P19: =IF(O19="Pass",1,IF(O19="Partial",0.5,IF(O19="Fail",0,"")))
A20: C2 | B20: Copilot Mode A classification | C20: Copilot A | D20: Classify the sales output step behind DM035. | E20: Holdout ON | F20: Matches the fit register; cites FUT material, not the register | H20: 1 | N20: Draft | P20: =IF(O20="Pass",1,IF(O20="Partial",0.5,IF(O20="Fail",0,"")))
A21: C3 | B21: Copilot Mode A classification | C21: Copilot A | D21: Classify the consignment steps. | E21: Holdout ON | F21: Matches the fit register; flags the Italian statutory element | H21: 1 | N21: Draft | P21: =IF(O21="Pass",1,IF(O21="Partial",0.5,IF(O21="Fail",0,"")))
A22: C4 | B22: Copilot Mode A classification | C22: Copilot A | D22: Classify a step that appears only in 'L2C FITs with missing description'. | E22: Holdout ON; pick one such step | F22: UNKNOWN or low confidence; no confident guess | H22: 1 | N22: Draft | P22: =IF(O22="Pass",1,IF(O22="Partial",0.5,IF(O22="Fail",0,"")))
A23: C5 | B23: Copilot Mode A classification | C23: Copilot A | D23: Classify 10 random L2C level-4 steps. | E23: Holdout ON; list the 10 codes in Notes | F23: Accuracy >= 80% on non-UNKNOWN; coverage >= 70% | H23: 1 | N23: Draft | P23: =IF(O23="Pass",1,IF(O23="Partial",0.5,IF(O23="Fail",0,"")))
A24: F1 | B24: Evidence & faithfulness | C24: Verifier | D24: For C1, show the exact sentences supporting the classification. | E24: Uses C1 output | F24: Every quote is a verbatim substring of its chunk | H24: 1 | L24: n/a | N24: Draft | P24: =IF(O24="Pass",1,IF(O24="Partial",0.5,IF(O24="Fail",0,"")))
A25: F2 | B25: Evidence & faithfulness | C25: Verifier | D25: Is there evidence against the C2 classification? | E25: Uses C2 output | F25: Lists 'against' evidence, or states none found | H25: 1 | L25: n/a | N25: Draft | P25: =IF(O25="Pass",1,IF(O25="Partial",0.5,IF(O25="Fail",0,"")))
A26: F3 | B26: Evidence & faithfulness | C26: Verifier | D26: Is the C3 evidence from a transcript or a specification? | E26: Uses C3 output | F26: Correct source type; confidence capped at 0.4 if only transcripts | H26: 1 | L26: n/a | N26: Draft | P26: =IF(O26="Pass",1,IF(O26="Partial",0.5,IF(O26="Fail",0,"")))
A27: F4 | B27: Evidence & faithfulness | C27: Verifier | D27: Verify an entry containing a chunk ID that was not retrieved. | E27: Inject a fake chunk ID | F27: Verifier rejects the entry | G27: Fabricated citation accepted | H27: 1 | L27: n/a | N27: Draft | P27: =IF(O27="Pass",1,IF(O27="Partial",0.5,IF(O27="Fail",0,"")))
A28: N1 | B28: Negative / unknown | C28: RAG + Copilot | D28: What is the e-invoicing mandate for Brazil in the template? | F28: States not in corpus (EXT has no Brazil material) | G28: Any invented mandate | H28: 2 | L28: n/a | N28: Draft | P28: =IF(O28="Pass",1,IF(O28="Partial",0.5,IF(O28="Fail",0,"")))
A29: N2 | B29: Negative / unknown | C29: RAG + Copilot | D29: Which SDD defines the returns process? | F29: States no SDD layer exists; points to config/FUT instead | G29: A named SDD | H29: 2 | L29: n/a | N29: Draft | P29: =IF(O29="Pass",1,IF(O29="Partial",0.5,IF(O29="Fail",0,"")))
A30: N3 | B30: Negative / unknown | C30: RAG + Copilot | D30: Who approved the credit-check design decision? | F30: Named approver only if stated in a document; else UNKNOWN | G30: An inferred approver | H30: 2 | L30: n/a | N30: Draft | P30: =IF(O30="Pass",1,IF(O30="Partial",0.5,IF(O30="Fail",0,"")))
A31: N4 | B31: Negative / unknown | C31: RAG + Copilot | D31: What is SPARK-99999? | E31: Fictitious ticket | F31: States not found | G31: Any description of the ticket | H31: 2 | L31: n/a | N31: Draft | P31: =IF(O31="Pass",1,IF(O31="Partial",0.5,IF(O31="Fail",0,"")))
A32: N5 | B32: Negative / unknown | C32: RAG + Copilot | D32: Classify BPML step 9.9.9.9. | E32: Code not in hierarchy | F32: Refuses: code not in the BPML hierarchy | G32: Any classification | H32: 2 | L32: n/a | N32: Draft | P32: =IF(O32="Pass",1,IF(O32="Partial",0.5,IF(O32="Fail",0,"")))
A33: L1 | B33: Leakage | C33: Copilot A | D33: Run C1–C5 with holdout ON, then OFF; compare accuracy. | E33: Two runs | F33: Accuracy gap < 10 points | H33: 1 | L33: n/a | N33: Draft | P33: =IF(O33="Pass",1,IF(O33="Partial",0.5,IF(O33="Fail",0,"")))
A34: L2 | B34: Leakage | C34: Copilot A | D34: With holdout ON: is 4.4.8.10 a FIT or a GAP? | E34: Holdout ON | F34: No citation from fit-register files or FIT/GAP folder paths | G34: Citation of a fit register | H34: 1 | L34: n/a | N34: Draft | P34: =IF(O34="Pass",1,IF(O34="Partial",0.5,IF(O34="Fail",0,"")))
A35: L3 | B35: Leakage | C35: Copilot A | D35: Check which graph edges derive from folder or file names. | E35: Inspect graph | F35: None are used in holdout mode | H35: 1 | L35: n/a | N35: Draft | P35: =IF(O35="Pass",1,IF(O35="Partial",0.5,IF(O35="Fail",0,"")))
A36: S1 | B36: Synthesis & decisions | C36: Copilot synthesis | D36: What percentage of L2C steps reuse the template unchanged? | E36: Full L2C run | F36: Figure reconciles to per-entry classes | H36: 1 | L36: n/a | N36: Draft | P36: =IF(O36="Pass",1,IF(O36="Partial",0.5,IF(O36="Fail",0,"")))
A37: S2 | B37: Synthesis & decisions | C37: Copilot synthesis | D37: Which 5 gaps are the most material? | E37: Full L2C run | F37: Sorted by materiality then confidence; all pricing/credit/billing/tax/interface | H37: 1 | L37: n/a | N37: Draft | P37: =IF(O37="Pass",1,IF(O37="Partial",0.5,IF(O37="Fail",0,"")))
A38: S3 | B38: Synthesis & decisions | C38: Copilot synthesis | D38: What decisions must Solvay make for consignment? | E38: Full L2C run | F38: 2–4 options each with evidence; no recommendation | G38: A recommended option | H38: 1 | L38: n/a | N38: Draft | P38: =IF(O38="Pass",1,IF(O38="Partial",0.5,IF(O38="Fail",0,"")))
A39: S4 | B39: Synthesis & decisions | C39: Copilot synthesis | D39: Which interfaces are affected by the gaps? | E39: Full L2C run | F39: Grouped by system; each backed by evidence | H39: 1 | L39: n/a | N39: Draft | P39: =IF(O39="Pass",1,IF(O39="Partial",0.5,IF(O39="Fail",0,"")))
A40: S5 | B40: Synthesis & decisions | C40: Copilot synthesis | D40: Build a workshop agenda for pricing and billing. | E40: Full L2C run | F40: Ordered by decision weight; pre-read links present | H40: 1 | L40: n/a | N40: Draft | P40: =IF(O40="Pass",1,IF(O40="Partial",0.5,IF(O40="Fail",0,"")))
A41: B1 | B41: Copilot Mode B country delta | C41: Copilot B | D41: Which L2C steps must change for the US (sales tax)? | E41: Sample US profile | F41: ADAPT/CHALLENGE with evidence; UNKNOWN where corpus is silent | H41: 1 | L41: n/a | N41: Draft | P41: =IF(O41="Pass",1,IF(O41="Partial",0.5,IF(O41="Fail",0,"")))
A42: B2 | B42: Copilot Mode B country delta | C42: Copilot B | D42: Can the Italian consignment register pattern be reused elsewhere? | E42: Sample profile | F42: CHALLENGE, flagged as Italy-specific statutory | H42: 1 | L42: n/a | N42: Draft | P42: =IF(O42="Pass",1,IF(O42="Partial",0.5,IF(O42="Fail",0,"")))
A43: B3 | B43: Copilot Mode B country delta | C43: Copilot B | D43: Which template customisations should be challenged before they travel? | E43: Sample profile | F43: Development items listed, each with an SAP-standard alternative question | H43: 1 | L43: n/a | N43: Draft | P43: =IF(O43="Pass",1,IF(O43="Partial",0.5,IF(O43="Fail",0,"")))
